bea_tools/__init__.py
bea_tools/utility.py
bea_tools/_dicom/dicomp.py
bea_tools/_matplotlib/general.py
bea_tools/_pandas/__init__.py
bea_tools/_pandas/sampler.py
bea_tools/_pandas/series.py
bea_tools/testing/_dicomp.py
bea_tools/testing/_matplotlib.py
bea_tools/testing/_pandas.py
bea_tools-0.0.9.dist-info/METADATA
bea_tools-0.0.9.dist-info/WHEEL
bea_tools-0.0.9.dist-info/top_level.txt
bea_tools-0.0.9.dist-info/RECORD
